utils/.DS_Store
utils/__init__.py
utils/abc.py
test1/.DS_Store
test1/__init__.py
test1/math.py
test1yyc-0.1.2.dist-info/METADATA
test1yyc-0.1.2.dist-info/WHEEL
test1yyc-0.1.2.dist-info/RECORD
