Metadata-Version: 2.1
Name: test1Yyc
Version: 0.1.2
Summary: 
Author: u7133414
Author-email: u7133414@anu.edu.au
Requires-Python: >=3.8,<4.0
Classifier: Programming Language :: Python :: 3
Classifier: Programming Language :: Python :: 3.8
Classifier: Programming Language :: Python :: 3.9
Classifier: Programming Language :: Python :: 3.10
Classifier: Programming Language :: Python :: 3.11
Classifier: Programming Language :: Python :: 3.12
Requires-Dist: flash (>=1.0.3,<2.0.0)
Requires-Dist: flask (>=3.0.3,<4.0.0)
